LICENSE.txt
README.md
setup.py
csciutils/__init__.py
csciutils.egg-info/PKG-INFO
csciutils.egg-info/SOURCES.txt
csciutils.egg-info/dependency_links.txt
csciutils.egg-info/requires.txt
csciutils.egg-info/top_level.txt
csciutils/BasicModels/__init__.py
csciutils/BasicModels/DMI/__init__.py
csciutils/BasicModels/DMI/utils.py
csciutils/BasicModels/DMI/General/__init__.py
csciutils/BasicModels/DMI/General/bondSearch.py
csciutils/BasicModels/DMI/General/search.py
csciutils/BasicModels/DMI/OffshoreBonds/__init__.py
csciutils/BasicModels/DMI/OffshoreBonds/IssueHistory/__init__.py
csciutils/BasicModels/DMI/OffshoreBonds/IssueHistory/issuehistory.py
csciutils/BasicModels/DMI/OffshoreBonds/NewIssue/__init__.py
csciutils/BasicModels/DMI/OffshoreBonds/NewIssue/newIssue.py
csciutils/BasicModels/DMI/OffshoreBonds/UnExpired/__init__.py
csciutils/BasicModels/DMI/OffshoreBonds/UnExpired/unexpired.py
csciutils/BasicModels/DOCX/__init__.py
csciutils/BasicModels/DOCX/docx.py
csciutils/BasicModels/Inputs/__init__.py
csciutils/BasicModels/Inputs/inputs.py
csciutils/BasicModels/PreKYCCC/__init__.py
csciutils/BasicModels/PreKYCCC/checklist.py
csciutils/BasicModels/Proxy/__init__.py
csciutils/BasicModels/Proxy/proxy.py
csciutils/BasicModels/QYYJT/__init__.py
csciutils/BasicModels/QYYJT/company.py
csciutils/BasicModels/QYYJT/fakelogin.py
csciutils/BasicModels/QYYJT/fetchinfo.py
csciutils/BasicModels/QYYJT/generalsearch.py
csciutils/BasicModels/QYYJT/login.py
csciutils/BasicModels/Tianyancha/__init__.py
csciutils/BasicModels/Tianyancha/tianyancha.py
csciutils/BasicModels/WorldCheck/__init__.py
csciutils/BasicModels/WorldCheck/appendixc.py
csciutils/BasicModels/WorldCheck/worldcheck.py
csciutils/BasicModels/iFinD/__init__.py
csciutils/BasicModels/iFinD/basic.py
csciutils/BasicModels/iFinD/business_info.py
csciutils/Wrappers/__init__.py
csciutils/Wrappers/validations.py