Metadata-Version: 2.4
Name: csciutils
Version: 2.1.2
Summary: 中信建投国际自动化工作
Author: ZhuBowen
Author-email: zhubowen@gmail.com
Classifier: Programming Language :: Python :: 3
Classifier: License :: OSI Approved :: MIT License
Classifier: Operating System :: OS Independent
Requires-Python: >=3.6
License-File: LICENSE.txt
Requires-Dist: requests>=2.28.1
Requires-Dist: selenium>=4.24.0
Dynamic: author
Dynamic: author-email
Dynamic: classifier
Dynamic: description
Dynamic: description-content-type
Dynamic: license-file
Dynamic: requires-dist
Dynamic: requires-python
Dynamic: summary
